README.md
setup.py
stylelens_dataset/__init__.py
stylelens_dataset/categories.py
stylelens_dataset/colors.py
stylelens_dataset/database.py
stylelens_dataset/images.py
stylelens_dataset/labels.py
stylelens_dataset/objects.py
stylelens_dataset/texts.py
stylelens_dataset.egg-info/PKG-INFO
stylelens_dataset.egg-info/SOURCES.txt
stylelens_dataset.egg-info/dependency_links.txt
stylelens_dataset.egg-info/requires.txt
stylelens_dataset.egg-info/top_level.txt