Metadata-Version: 1.0
Name: stylelens-dataset
Version: 0.0.31
Summary: stylelens-dataset
Home-page: UNKNOWN
Author: UNKNOWN
Author-email: master@bluehack.net
License: UNKNOWN
Keywords: BlueLens,stylelens-dataset
Platform: UNKNOWN
